mozi_cross_val/__init__.py
mozi_cross_val/filters/__init__.py
mozi_cross_val/filters/base_filter.py
mozi_cross_val/filters/loader.py
mozi_cross_val/filters/overfitness_filters.py
mozi_cross_val/filters/score_filters.py
mozi_cross_val/main/__init__.py
mozi_cross_val/main/cross_val.py
mozi_cross_val/main/model_evaluator.py
mozi_cross_val/main/moses_runner.py
mozi_cross_val/main/post_process.py
mozi_cross_val/models/__init__.py
mozi_cross_val/models/objmodel.py
mozi_cross_val/utils/__init__.py
mozi_cross_val/utils/config.py
mozi_cross_val/utils/feature_count.py
tests/__init__.py
tests/test_combo_parser.py
tests/test_model_evaluator.py
tests/test_moses_cross_val.py
tests/test_moses_runner.py
tests/test_score_filter.py
moses_crossval-0.6.dist-info/LICENSE
moses_crossval-0.6.dist-info/METADATA
moses_crossval-0.6.dist-info/WHEEL
moses_crossval-0.6.dist-info/top_level.txt
moses_crossval-0.6.dist-info/RECORD
